rmotr_curriculum_tools/__init__.py
rmotr_curriculum_tools/exceptions.py
rmotr_curriculum_tools/io.py
rmotr_curriculum_tools/models.py
rmotr_curriculum_tools/testing.py
rmotr_curriculum_tools/utils.py
rmotr_curriculum_tools-0.3.1.data/scripts/main.py
rmotr_curriculum_tools-0.3.1.dist-info/METADATA
rmotr_curriculum_tools-0.3.1.dist-info/WHEEL
rmotr_curriculum_tools-0.3.1.dist-info/entry_points.txt
rmotr_curriculum_tools-0.3.1.dist-info/top_level.txt
rmotr_curriculum_tools-0.3.1.dist-info/zip-safe
rmotr_curriculum_tools-0.3.1.dist-info/RECORD
