Metadata-Version: 2.1
Name: rmotr-curriculum-tools
Version: 0.3.1
Summary: A set of tools to ease the work with rmotr.com curriculum
Home-page: http://github.com/rmotr/rmotr-curriculum-tools
Author: Santiago Basulto
Author-email: santiago.basulto@gmail.com
Maintainer: Santiago Basulto
License: MIT
Platform: UNKNOWN
Requires-Dist: click (==6.3)
Requires-Dist: pytoml (==0.1.7)
Requires-Dist: py-gfm (==0.1.2)
Requires-Dist: Markdown (==2.6.6)
Requires-Dist: beautifulsoup4 (==4.4.1)
Requires-Dist: colorama (==0.3.7)
Requires-Dist: colorlog (==3.1.0)
